MANIFEST.in
README.md
setup.py
cellworld_gym/README.md
cellworld_gym/__init__.py
cellworld_gym/core.py
cellworld_gym/license.txt
cellworld_gym/setup.cfg
cellworld_gym.egg-info/PKG-INFO
cellworld_gym.egg-info/SOURCES.txt
cellworld_gym.egg-info/dependency_links.txt
cellworld_gym.egg-info/not-zip-safe
cellworld_gym.egg-info/requires.txt
cellworld_gym.egg-info/top_level.txt
cellworld_gym/__pycache__/__init__.cpython-312.pyc
cellworld_gym/__pycache__/core.cpython-312.pyc
cellworld_gym/envs/__init__.py
cellworld_gym/envs/bot_evade.py
cellworld_gym/envs/bot_evade_belief.py
cellworld_gym/envs/dual_evade.py
cellworld_gym/envs/oasis.py
cellworld_gym/envs/__pycache__/__init__.cpython-312.pyc
cellworld_gym/envs/__pycache__/bot_evade.cpython-312.pyc
cellworld_gym/envs/__pycache__/bot_evade_belief.cpython-312.pyc
cellworld_gym/envs/__pycache__/dual_evade.cpython-312.pyc
cellworld_gym/envs/__pycache__/oasis.cpython-312.pyc