Metadata-Version: 2.1
Name: cellworld_gym
Version: 0.0.126
Summary: OpenAI gym environments for cellworld experimental setup
Home-page: https://github.com/germanespinosa/cellworld_gym
Author: German Espinosa
Author-email: germanespinosa@gmail.com
License: MIT
Requires-Dist: cellworld_game
Requires-Dist: cellworld_belief
Requires-Dist: gym
